generic_consumer/__init__.py
generic_consumer/generic_consumer.py
generic_consumer/logger.py
generic_consumer/passive_consumer.py
generic_consumer/pipeline.py
generic_consumer/signal.py
generic_consumer/strings.py
generic_consumer-0.20.2.dist-info/METADATA
generic_consumer-0.20.2.dist-info/WHEEL
generic_consumer-0.20.2.dist-info/RECORD
