Metadata-Version: 2.3
Name: generic-consumer
Version: 0.20.2
Summary: A generic consumer for Python.
Author: Mister Nyan
Author-email: michael.edmund.wong@gmail.com
Requires-Python: >=3.8,<4.0
Classifier: Programming Language :: Python :: 3
Classifier: Programming Language :: Python :: 3.8
Classifier: Programming Language :: Python :: 3.9
Classifier: Programming Language :: Python :: 3.10
Classifier: Programming Language :: Python :: 3.11
Classifier: Programming Language :: Python :: 3.12
Classifier: Programming Language :: Python :: 3.13
Requires-Dist: fun-things
Requires-Dist: simple-chalk
